db/__init__.py
db/elastic_auth.py
db/search_tools.py
search/__init__.py
search/knn_search.py
gp_mlsearch-0.2.0.dist-info/METADATA
gp_mlsearch-0.2.0.dist-info/WHEEL
gp_mlsearch-0.2.0.dist-info/top_level.txt
gp_mlsearch-0.2.0.dist-info/RECORD
