Metadata-Version: 2.4
Name: gp-mlsearch
Version: 0.2.0
Summary: K-NN + Elasticsearch helpers
Author-email: Isaac Kontomah <isaac.kontomah@growthprotocol.ai>
License: MIT
Requires-Python: >=3.9
Requires-Dist: elasticsearch>=8.13
Requires-Dist: sentence-transformers>=2.6
